MLTranslit/MLTranslit.py
MLTranslit/__init__.py
MLTranslit-1.0.5.dist-info/LICENCE.md
MLTranslit-1.0.5.dist-info/METADATA
MLTranslit-1.0.5.dist-info/WHEEL
MLTranslit-1.0.5.dist-info/top_level.txt
MLTranslit-1.0.5.dist-info/RECORD
